Workbook

Sheet Assumptions
A1: Marico FCFF DCF — Forecast Assumptions
A3: Assumption | B3: FY26E (B) | C3: FY27E (C) | D3: FY28E (D)
A4: Revenue Growth | B4: 0.0553 | C4: 0.0553 | D4: 0.0553
A5: EBITDA Margin | B5: 0.1976 | C5: 0.1976 | D5: 0.1976
A6: Tax Rate | B6: 0.2275 | C6: 0.2275 | D6: 0.2275
A7: Capex as % of Revenue | B7: 0.0165 | C7: 0.0165 | D7: 0.0165
A8: D&A as % of Revenue | B8: 0.0162 | C8: 0.0162 | D8: 0.0162
A9: Trade Receivables as % of Revenue | B9: 0.1107 | C9: 0.1107 | D9: 0.1107
A10: Inventories as % of Revenue | B10: 0.126 | C10: 0.126 | D10: 0.126
A11: Other Operating Current Assets as % of Revenue | B11: 0.0336 | C11: 0.0336 | D11: 0.0336
A12: Trade Payables as % of Revenue | B12: 0.1461 | C12: 0.1461 | D12: 0.1461
A13: Other Operating Current Liabilities as % of Revenue | B13: 0.0218 | C13: 0.0218 | D13: 0.0218

Sheet Forecast
A1: Category | B1: Metric | C1: FY23A | D1: FY24A | E1: FY25A | F1: FY26E | G1: FY27E | H1: FY28E | I1: Unit | J1: Source / Formula
A2: Revenue | B2: Revenue from Operations | C2: =Historical_Data!C2 -> 9764 | D2: =Historical_Data!D2 -> 9653 | E2: =Historical_Data!E2 -> 10831 | F2: =E2*(1+Assumptions!B4) -> 11429.954 | G2: =F2*(1+Assumptions!C4) -> 12062.031 | H2: =G2*(1+Assumptions!D4) -> 12729.061 | I2: ₹ crore
A3: Revenue | B3: Revenue Growth | D3: =D2/C2-1 -> -0.011368292 | E3: =E2/D2-1 -> 0.1220346 | F3: =F2/E2-1 -> 0.0553 | G3: =G2/F2-1 -> 0.0553 | H3: =H2/G2-1 -> 0.0553 | I3: %
A4: Revenue | B4: Other Income | C4: =Historical_Data!C3 -> 144 | D4: =Historical_Data!D3 -> 142 | E4: =Historical_Data!E3 -> 208 | I4: ₹ crore
A5: Profitability | B5: EBITDA | C5: =Historical_Data!C4 -> 1810 | D5: =Historical_Data!D4 -> 2026 | E5: =Historical_Data!E4 -> 2139 | F5: =F2*Assumptions!B5 -> 2258.559 | G5: =G2*Assumptions!C5 -> 2383.4573 | H5: =H2*Assumptions!D5 -> 2515.2625 | I5: ₹ crore
A6: Profitability | B6: EBITDA Margin | C6: =C5/C2 -> 0.18537485 | D6: =D5/D2 -> 0.20988294 | E6: =E5/E2 -> 0.19748869 | I6: %
A7: Profitability | B7: Depreciation & Amortisation | C7: =Historical_Data!C6 -> 155 | D7: =Historical_Data!D6 -> 158 | E7: =Historical_Data!E6 -> 178 | F7: =F2*Assumptions!B8 -> 185.16526 | G7: =G2*Assumptions!C8 -> 195.4049 | H7: =H2*Assumptions!D8 -> 206.21079 | I7: ₹ crore
A8: Profitability | B8: EBIT | C8: =(C5-C7) -> 1655 | D8: =(D5-D7) -> 1868 | E8: =(E5-E7) -> 1961 | F8: =F5-F7 -> 2073.3937 | G8: =G5-G7 -> 2188.0524 | H8: =H5-H7 -> 2309.0517 | I8: ₹ crore
A9: Profitability | B9: EBIT Margin | C9: =C8/C2 -> 0.1695002 | D9: =D8/D2 -> 0.19351497 | E9: =E8/E2 -> 0.18105438 | F9: =F8/F2 -> 0.1814 | G9: =G8/G2 -> 0.1814 | H9: =H8/H2 -> 0.1814 | I9: %
A10: Profitability | B10: PBT | C10: =Historical_Data!C9 -> 1743 | D10: =Historical_Data!D9 -> 1937 | E10: =Historical_Data!E9 -> 2116
A11: Tax | B11: Tax Expense | C11: =Historical_Data!C10 -> 421 | D11: =Historical_Data!D10 -> 435 | E11: =Historical_Data!E10 -> 458 | I11: ₹ crore
A12: Tax | B12: Tax Rate | C12: =C11/C10 -> 0.24153758 | D12: =D11/D10 -> 0.22457408 | E12: =E11/E10 -> 0.21644612 | F12: =Assumptions!B6 -> 0.2275 | G12: =Assumptions!C6 -> 0.2275 | H12: =Assumptions!D6 -> 0.2275 | I12: %
A13: Profitability | B13: NOPAT | C13: =C8*(1-C12) -> 1255.2553 | D13: =D8*(1-D12) -> 1448.4956 | E13: =E8*(1-E12) -> 1536.5491 | F13: =F8*(1-F12) -> 1601.6966 | G13: =G8*(1-G12) -> 1690.2705 | H13: =H8*(1-H12) -> 1783.7424 | I13: ₹ crore
A14: Cash Flow | B14: Capital Expenditure | C14: =Historical_Data!C12 -> 182 | D14: =Historical_Data!D12 -> 153 | E14: =Historical_Data!E12 -> 161 | F14: =F2*Assumptions!B7 -> 188.59425 | G14: =G2*Assumptions!C7 -> 199.02351 | H14: =H2*Assumptions!D7 -> 210.02951 | I14: ₹ crore
A15: Cash Flow | B15: D&A | C15: =Historical_Data!C13 -> 155 | D15: =Historical_Data!D13 -> 158 | E15: =Historical_Data!E13 -> 178 | F15: =F7 -> 185.16526 | G15: =G7 -> 195.4049 | H15: =H7 -> 206.21079 | I15: ₹ crore
A16: Working Capital | B16: Trade Receivables | C16: =Historical_Data!C15 -> 1015 | D16: =Historical_Data!D15 -> 1069 | E16: =Historical_Data!E15 -> 1271 | F16: =F2*Assumptions!B9 -> 1265.2959 | G16: =G2*Assumptions!C9 -> 1335.2668 | H16: =H2*Assumptions!D9 -> 1409.1071 | I16: ₹ crore
A17: Working Capital | B17: Inventories | C17: =Historical_Data!C16 -> 1225 | D17: =Historical_Data!D16 -> 1336 | E17: =Historical_Data!E16 -> 1235 | F17: =F2*Assumptions!B10 -> 1440.1742 | G17: =G2*Assumptions!C10 -> 1519.8159 | H17: =H2*Assumptions!D10 -> 1603.8617 | I17: ₹ crore
A18: Working Capital | B18: Other Operating Current Assets | C18: =Historical_Data!C17 -> 229 | D18: =Historical_Data!D17 -> 378 | E18: =Historical_Data!E17 -> 413 | F18: =F2*Assumptions!B11 -> 384.04646 | G18: =G2*Assumptions!C11 -> 405.28423 | H18: =H2*Assumptions!D11 -> 427.69645 | I18: ₹ crore
A19: Working Capital | B19: Trade Payables | C19: =Historical_Data!C18 -> 1452 | D19: =Historical_Data!D18 -> 1581 | E19: =Historical_Data!E18 -> 1363 | F19: =F2*Assumptions!B12 -> 1669.9163 | G19: =G2*Assumptions!C12 -> 1762.2627 | H19: =H2*Assumptions!D12 -> 1859.7158 | I19: ₹ crore
A20: Working Capital | B20: Other Operating Current Liabilities | C20: =Historical_Data!C19 -> 217 | D20: =Historical_Data!D19 -> 211 | E20: =Historical_Data!E19 -> 232 | F20: =F2*Assumptions!B13 -> 249.173 | G20: =G2*Assumptions!C13 -> 262.95227 | H20: =H2*Assumptions!D13 -> 277.49353 | I20: ₹ crore
A21: Working Capital | B21: Operating Net Working Capital | C21: =C16+C17+C18-C19-C20 -> 800 | D21: =D16+D17+D18-D19-D20 -> 991 | E21: =E16+E17+E18-E19-E20 -> 1324 | F21: =F16+F17+F18-F19-F20 -> 1170.4273 | G21: =G16+G17+G18-G19-G20 -> 1235.152 | H21: =H16+H17+H18-H19-H20 -> 1303.4559 | I21: ₹ crore
A22: Working Capital | B22: Change in NWC | D22: =D21-C21 -> 191 | E22: =E21-D21 -> 333 | F22: =F21-E21 -> -153.57268 | G22: =G21-F21 -> 64.724631 | H22: =H21-G21 -> 68.303903 | I22: ₹ crore

Sheet FCFF
A1: FCFF Calculation
A3: Metric | B3: FY26E | C3: FY27E | D3: FY28E
A4: NOPAT | B4: =Forecast!F13 -> 1601.6966 | C4: =Forecast!G13 -> 1690.2705 | D4: =Forecast!H13 -> 1783.7424
A5: D&A | B5: =Forecast!F15 -> 185.16526 | C5: =Forecast!G15 -> 195.4049 | D5: =Forecast!H15 -> 206.21079
A6: Capital Expenditure | B6: =Forecast!F14 -> 188.59425 | C6: =Forecast!G14 -> 199.02351 | D6: =Forecast!H14 -> 210.02951
A7: Change in NWC | B7: =Forecast!F22 -> -153.57268 | C7: =Forecast!G22 -> 64.724631 | D7: =Forecast!H22 -> 68.303903
A8: FCFF | B8: =B4+B5-B6-B7 -> 1751.8403 | C8: =C4+C5-C6-C7 -> 1621.9272 | D8: =D4+D5-D6-D7 -> 1711.6198

Sheet WACC_DCF
A1: WACC Calculation
A3: Component | B3: Value
A4: Risk-Free Rate | B4: 0.06582
A5: Beta | B5: 0.44191026
A6: Market Risk Premium | B6: 0.09
A7: Cost of Equity | B7: =B4+B5*B6 -> 0.10559192
A8: Pre-Tax Cost of Debt | B8: 0.057
A9: Tax Rate | B9: =Assumptions!B6 -> 0.2275
A10: After-Tax Cost of Debt | B10: =B8*(1-B9) -> 0.0440325 | G10: Marico FCFF DCF — Sensitivity Analysis
A11: Market Value of Equity | B11: 84421.127
A12: Debt Value | B12: =Historical_Data!E23 -> 379 | G12: =$B$35 -> 24361.584 | H12: 0.03 | I12: 0.035 | J12: 0.04 | K12: 0.045 | L12: 0.05
A13: Total Capital | B13: =B11+B12 -> 84800.127 | G13: 0.07 | H13: 40428.764 | I13: 45768.031 | J13: 52887.055 | K13: 62853.689 | L13: 77803.639
A14: Equity Weight | B14: =B11/B13 -> 0.99553067 | G14: 0.075 | H14: 35946.913 | I14: 40061.136 | J14: 45350.852 | K14: 52403.807 | L14: 62277.943
A15: Debt Weight | B15: =B12/B13 -> 0.0044693329 | G15: 0.08 | H15: 32361.378 | I15: 35622.351 | J15: 39698.568 | K15: 44939.418 | L15: 51927.219
A16: WACC | B16: =IF(B17="",B14*B7+B15*B10,B17) -> 0.10531679 | G16: 0.085 | H16: 29427.708 | I16: 32071.244 | J16: 35302.232 | K16: 39340.966 | L16: 44533.625
A17: WACC Override (Sensitivity Only) | G17: 0.09 | H17: 26982.939 | I17: 29165.721 | J17: 31785.06 | K17: 34986.473 | L17: 38988.24
A18: Terminal Value
A19: Terminal Growth Rate | B19: 0.04
A20: FY28E FCFF | B20: =FCFF!D8 -> 1711.6198
A21: Terminal Year FCFF | B21: =B20*(1+B19) -> 1780.0846
A22: Terminal Value | B22: =IF(B16<=B19,NA(),B21/(B16-B19)) -> 27253.092
A23: PV Factor — FY28E | B23: =1/(1+$B$16)^3 -> 0.74052495
A24: Present Value of Terminal Value | B24: =B22*B23 -> 20181.594
A26: DCF Valuation
A27: Metric | B27: FY26E | C27: FY27E | D27: FY28E
A28: FCFF | B28: =FCFF!B8 -> 1751.8403 | C28: =FCFF!C8 -> 1621.9272 | D28: =FCFF!D8 -> 1711.6198
A29: Discount Period | B29: =1 -> 1 | C29: =2 -> 2 | D29: =3 -> 3
A30: Discount Factor | B30: =1/(1+$B$16)^B29 -> 0.904718 | C30: =1/(1+$B$16)^C29 -> 0.81851466 | D30: =1/(1+$B$16)^3 -> 0.74052495
A31: PV of FCFF | B31: =B28*B30 -> 1584.9215 | C31: =C28*C30 -> 1327.5712 | D31: =D28*D30 -> 1267.4972
A33: PV of Explicit FCFF | B33: =SUM(B31:D31) -> 4179.9899
A34: PV of Terminal Value | B34: =B24 -> 20181.594
A35: Enterprise Value | B35: =B33 + B34 -> 24361.584

Sheet Historical_Data
A1: Category | B1: Metric | C1: FY23 | D1: FY24 | E1: FY25 | F1: Unit | G1: FY23 Source | H1: FY23 Page | I1: FY24 Source | J1: FY24 Page | K1: FY25 Source | L1: FY25 Page | M1: Notes
A2: Revenue | B2: Revenue from Operations | C2: 9764 | D2: 9653 | E2: 10831 | F2: ₹ crore | G2: S-002 | H2: 388-389 | I2: S-002 | J2: 388-389 | K2: S-001 | L2: 380-381 | M2: Consolidated financial statements; Note 19
A3: Revenue | B3: Other Income | C3: 144 | D3: 142 | E3: 208 | F3: ₹ crore | G3: S-002 | H3: 388-389 | I3: S-002 | J3: 388-389 | K3: S-001 | L3: 380-381 | M3: Consolidated financial statements; Note 20
A4: Profitability | B4: EBITDA | C4: 1810 | D4: 2026 | E4: 2139 | F4: ₹ crore | G4: S-002 | H4: 216-217 | I4: S-002 | J4: 502-503 | K4: S-001 | L4: 500-501
A5: Profitability | B5: EBITDA Margin | C5: =(C4/C2) -> 0.18537485 | D5: =(D4/D2) -> 0.20988294 | E5: =(E4/E2) -> 0.19748869 | F5: % | G5: Calculated | I5: Calculated | K5: Calculated | M5: Calculated as EBITDA / Revenue from Operations
A6: Profitability | B6: Depreciation & Amortisation | C6: 155 | D6: 158 | E6: 178 | F6: ₹ crore | G6: S-002 | H6: 502-503 | I6: S-002 | J6: 502-503 | K6: S-001 | L6: 500-501 | M6: Consolidated financial performance
A7: Profitability | B7: EBIT | C7: =(C4-C6) -> 1655 | D7: =(D4-D6) -> 1868 | E7: =(E4-E6) -> 1961 | F7: ₹ crore | G7: Calculated | I7: Calculated | K7: Calculated | M7: Calculated as EBITDA less D&A; excludes Other Income for FCFF operating EBIT
A8: Profitability | B8: Finance Cost | C8: 56 | D8: 73 | E8: 53 | F8: ₹ crore | G8: S-002 | H8: 502-503 | I8: S-002 | J8: 502-503 | K8: S-001 | L8: 500-501
A9: Profitability | B9: Profit Before Tax | C9: 1743 | D9: 1937 | E9: 2116 | F9: ₹ crore | G9: S-002 | H9: 502-503 | I9: S-002 | J9: 502-503 | K9: S-001 | L9: 500-501
A10: Tax | B10: Tax Expense | C10: 421 | D10: 435 | E10: 458 | F10: ₹ crore | G10: S-002 | H10: 502-503 | I10: S-002 | J10: 502-503 | K10: S-001 | L10: 500-501
A11: Profitability | B11: Profit After Tax | C11: 1322 | D11: 1502 | E11: 1658 | F11: ₹ crore | G11: S-002 | H11: 502-503 | I11: S-002 | J11: 502-503 | K11: S-001 | L11: 500-501
A12: Cash Flow | B12: Capital Expenditure | C12: 182 | D12: 153 | E12: 161 | F12: ₹ crore | G12: S-002 | H12: 80-81 | I12: S-002 | J12: 80-81 | K12: S-001 | L12: 66-67 | M12: Capital expenditure for capacity expansion and maintenance; consolidated
A13: Cash Flow | B13: Depreciation & Amortisation — Cash Flow Add-back | C13: 155 | D13: 158 | E13: 178
A14: Cash Flow | B14: Cash Flow from Operating Activities | C14: 1419 | D14: 1436 | E14: 1363 | F14: ₹ crore | G14: S-002 | H14: 346-347 | I14: S-002 | J14: 346-347 | K14: S-001 | L14: 338-339 | M14: Net cash generated from operating activities; FY24 source report presents ₹1,436 crore
A15: Working Capital | B15: Trade Receivables | C15: 1015 | D15: 1069 | E15: 1271 | F15: ₹ crore | G15: S-002 | H15: 342-343 | I15: S-002 | J15: 342-343 | K15: S-001 | L15: 334-335 | M15: Consolidated balance sheet; Note 6(b)
A16: Working Capital | B16: Inventories | C16: 1225 | D16: 1336 | E16: 1235 | F16: ₹ crore | G16: S-002 | H16: 342-343 | I16: S-002 | J16: 342-343 | K16: S-001 | L16: 334-335 | M16: Consolidated balance sheet; Note 9
A17: Working Capital | B17: Other Operating Current Assets | C17: 229 | D17: 378 | E17: 413 | F17: ₹ crore | G17: S-002 | H17: 372-373 | I17: S-002 | J17: 372-373 | K17: S-001 | L17: 364-365 | M17: Other current assets; FY25 corrected to ₹413 crore per consolidated balance sheet in Marico FY25 Integrated Annual Report, p. 334-335.
A18: Working Capital | B18: Trade Payables | C18: 1452 | D18: 1581 | E18: 1363 | F18: ₹ crore | G18: S-002 | H18: 380-381 | I18: S-002 | J18: 380-381 | K18: S-001 | L18: 372-373 | M18: Consolidated trade payables; Note 13(c)
A19: Working Capital | B19: Other Operating Current Liabilities | C19: 217 | D19: 211 | E19: 232 | F19: ₹ crore | G19: S-002 | H19: 388-389 | I19: S-002 | J19: 388-389 | K19: S-001 | L19: 380-381 | M19: Other current liabilities; treated as operating current liabilities for NWC
A20: Working Capital | B20: Operating Net Working Capital | C20: =SUM(C15:C17)-C18-C19 -> 800 | D20: =D15+D16+D17-D18-D19 -> 991 | E20: =E15+E16+E17-E18-E19 -> 1324 | F20: ₹ crore | G20: Calculated | I20: Calculated | K20: Calculated | M20: Calculated as Trade Receivables + Inventories + Other Operating Current Assets − Trade Payables − Other Operating Current Liabilities
A21: Balance Sheet | B21: Cash & Cash Equivalents | C21: 207 | D21: 228 | E21: 321 | F21: ₹ crore | G21: S-002 | H21: 342-343 | I21: S-002 | J21: 342-343 | K21: S-001 | L21: 334-335 | M21: Consolidated balance sheet; Note 6(d)
A22: Balance Sheet | B22: Other Cash / Liquid Investments | C22: 578 | D22: 259 | E22: 1375 | F22: ₹ crore | G22: S-002 | H22: 342-343 | I22: S-002 | J22: 342-343 | K22: S-001 | L22: 334-335 | M22: Current investments; treated as liquid investments for enterprise-to-equity bridge
A23: Debt | B23: Borrowings | C23: 475 | D23: 383 | E23: 379 | F23: ₹ crore | G23: S-002 | H23: 342-343 | I23: S-002 | J23: 342-343 | K23: S-001 | L23: 334-335 | M23: Consolidated borrowings; includes current and non-current borrowings
A24: Equity | B24: Equity Share Capital | C24: 129 | D24: 129 | E24: 130 | F24: ₹ crore | G24: S-002 | H24: 342-343 | I24: S-002 | J24: 342-343 | K24: S-001 | L24: 334-335 | M24: Reported consolidated equity share capital; FY25 balance-sheet amount rounds to ₹130 crore
A25: Equity | B25: Shares Outstanding | C25: 129.3084 | D25: 129.4102 | E25: 129.5498 | F25: crore shares | G25: S-002 | H25: 372-373 | I25: S-002 | J25: 372-373 | K25: S-001 | L25: 362-363 | M25: Issued, subscribed and paid-up equity shares; converted to crore shares

Sheet Audit
A1: Audit check | B1: Results
A3: Base WACC positive; no manual override | B3: =IF(AND(WACC_DCF!B16>0,WACC_DCF!B17=""),"PASS","FAIL") -> PASS
A4: Terminal growth < WACC | B4: =IF(WACC_DCF!B19<WACC_DCF!B16,"PASS","FAIL") -> PASS
A5: Terminal value is positive | B5: =IF(WACC_DCF!B22>0,"PASS","FAIL") -> PASS
A6: Enterprise value reconciliation | B6: =IF(ABS(WACC_DCF!B35-(WACC_DCF!B33+WACC_DCF!B34))<0.01,"PASS","FAIL") -> PASS
A7: Sensitivity table complete | B7: =IF(COUNTA(WACC_DCF!H13:L17)=25,"PASS","FAIL") -> PASS
A8: Sensitivity directional check | B8: =IF(AND(WACC_DCF!L13>WACC_DCF!I13,WACC_DCF!I13>WACC_DCF!I17),"PASS","FAIL") -> PASS
A9: Forecast assumptions are linked | B9: =IF(AND(Forecast!F5=Forecast!F2*Assumptions!B5,Forecast!G5=Forecast!G2*Assumptions!C5,Forecast!H5=Forecast!H2*Assumptions!D5,Forecast!F12=Assumptions!B6,Forecast!G12=Assumptions!C6,Forecast!H12=Assumptions!D6),"PASS","FAIL") -> PASS
A10: Historical revenue tie-out | B10: =IF(AND(Forecast!C2=Historical_Data!C2,Forecast!D2=Historical_Data!D2,Forecast!E2=Historical_Data!E2),"PASS","FAIL") -> PASS
A11: FCFF reconciliation | B11: =IF(AND(ABS(FCFF!B8-(FCFF!B4+FCFF!B5-FCFF!B6-FCFF!B7))<0.01,ABS(FCFF!C8-(FCFF!C4+FCFF!C5-FCFF!C6-FCFF!C7))<0.01,ABS(FCFF!D8-(FCFF!D4+FCFF!D5-FCFF!D6-FCFF!D7))<0.01),"PASS","FAIL") -> PASS
A12: Formula-driven WACC chain | B12: =IF(ABS(WACC_DCF!B16-(WACC_DCF!B14*WACC_DCF!B7+WACC_DCF!B15*WACC_DCF!B10))<0.000001,"PASS","FAIL") -> PASS

Sheet Source_Notes
A1: Source_Notes
A3: Valuation date | B3: 31 March 2025. The prior trading day (28 March 2025) is used where the market was closed.
A4: Financial statements | B4: https://marico.com/investorspdf/Marico_Annual_Report_FY25.pdf
A5: Risk-free rate | B5: https://economictimes.indiatimes.com/markets/bonds/india-10-year-bond-yield-sees-biggest-drop-in-half-a-decade-on-foreign-flows-rate-cut/articleshow/119653311.cms
A6: India equity-risk premium | B6: https://pages.stern.nyu.edu/~adamodar/pdfiles/country/val2dayIndia2025.pdf
A7: Beta price series | B7: https://finance.yahoo.com/quote/MARICO.NS/history/ and https://finance.yahoo.com/quote/%5ENSEI/history/
A8: Calculation note | B8: Beta is an analyst calculation using 261 weekly adjusted-return observations ending 30 March 2025.
